{
  "project_info": {
    "project_number": "1043485449559",
    "firebase_url": "https://cloudlib-980ef-default-rtdb.europe-west1.firebasedatabase.app",
    "project_id": "cloudlib-980ef",
    "storage_bucket": "cloudlib-980ef.appspot.com"
  },
  "client": [
    {
      "client_info": {
        "mobilesdk_app_id": "1:1043485449559:android:c8c4de9559e7e4a9f0f212",
        "android_client_info": {
          "package_name": "com.example.myapplication"
        }
      },
      "oauth_client": [
        {
          "client_id": "1043485449559-ras2i17v7rl8b7jp47psov2vjiehfk3g.apps.googleusercontent.com",
          "client_type": 3
        }
      ],
      "api_key": [
        {
          "current_key": "AIzaSyAl9S1lsDJlgDwGObmK4ejS9qlIq4w92qg"
        }
      ],
      "services": {
        "appinvite_service": {
          "other_platform_oauth_client": [
            {
              "client_id": "1043485449559-ras2i17v7rl8b7jp47psov2vjiehfk3g.apps.googleusercontent.com",
              "client_type": 3
            }
          ]
        }
      }
    },
    {
      "client_info": {
        "mobilesdk_app_id": "1:1043485449559:android:d18b68a50b6cd8a1f0f212",
        "android_client_info": {
          "package_name": "pl.edu.pg.cloudlib"
        }
      },
      "oauth_client": [
        {
          "client_id": "1043485449559-ras2i17v7rl8b7jp47psov2vjiehfk3g.apps.googleusercontent.com",
          "client_type": 3
        }
      ],
      "api_key": [
        {
          "current_key": "AIzaSyAl9S1lsDJlgDwGObmK4ejS9qlIq4w92qg"
        }
      ],
      "services": {
        "appinvite_service": {
          "other_platform_oauth_client": [
            {
              "client_id": "1043485449559-ras2i17v7rl8b7jp47psov2vjiehfk3g.apps.googleusercontent.com",
              "client_type": 3
            }
          ]
        }
      }
    }
  ],
  "configuration_version": "1"
}